uart2ip/__init__.py
uart2ip/conf.py
uart2ip/initialization.py
uart2ip/ip.py
uart2ip/main.py
uart2ip/tasks.py
reactive_uart2ip-0.2.1.dist-info/LICENSE
reactive_uart2ip-0.2.1.dist-info/METADATA
reactive_uart2ip-0.2.1.dist-info/WHEEL
reactive_uart2ip-0.2.1.dist-info/entry_points.txt
reactive_uart2ip-0.2.1.dist-info/top_level.txt
reactive_uart2ip-0.2.1.dist-info/RECORD
