Metadata-Version: 2.1
Name: reactive-uart2ip
Version: 0.2.1
Summary: TCP server that mediates UART serial communication
Home-page: https://github.com/AuthenticExecution/reactive-uart2ip
Author: Gianluca Scopelliti
Author-email: gianlu.1033@gmail.com
License: UNKNOWN
Platform: UNKNOWN
Classifier: Programming Language :: Python :: 3
Classifier: License :: OSI Approved :: MIT License
Classifier: Operating System :: POSIX :: Linux
Requires-Python: >=3.6
Requires-Dist: pyserial-asyncio (==0.5)
Requires-Dist: colorlog (==4.6.2)
Requires-Dist: reactive-net
